setup.cfg
setup.py
curcal/_init_.py
curcal/curcal.py
curcal.egg-info/PKG-INFO
curcal.egg-info/SOURCES.txt
curcal.egg-info/dependency_links.txt
curcal.egg-info/not-zip-safe
curcal.egg-info/top_level.txt