Metadata-Version: 1.0
Name: curcal
Version: 1.0
Summary: Prints the calendar and highlights the current day. [Cur]rent + [cal]endar
Home-page: UNKNOWN
Author: ImDeFoX
Author-email: nikitakopytov4339@gmail.com
License: UNKNOWN
Platform: UNKNOWN
